darthvader/__init__.py
darthvader/core/__init__.py
darthvader/core/anakin.py
darthvader/core/leia.py
darthvader/core/luke.py
darthvader/shell/run.sh
darthvader-0.1.1.dist-info/METADATA
darthvader-0.1.1.dist-info/WHEEL
darthvader-0.1.1.dist-info/RECORD
